Python2018NiandubaogaoWanzhengbanMaguaBianchengYi/README.md
Python2018NiandubaogaoWanzhengbanMaguaBianchengYi/__init__.py
Python2018NiandubaogaoWanzhengbanMaguaBianchengYi/__main__.py
Python2018NiandubaogaoWanzhengbanMaguaBianchengYi/file.pdf
Python2018NiandubaogaoWanzhengbanMaguaBianchengYi/index.html
python_2018_niandubaogao_wanzhengban_magua_biancheng_yi-2024.3.4.0.dist-info/METADATA
python_2018_niandubaogao_wanzhengban_magua_biancheng_yi-2024.3.4.0.dist-info/WHEEL
python_2018_niandubaogao_wanzhengban_magua_biancheng_yi-2024.3.4.0.dist-info/entry_points.txt
python_2018_niandubaogao_wanzhengban_magua_biancheng_yi-2024.3.4.0.dist-info/top_level.txt
python_2018_niandubaogao_wanzhengban_magua_biancheng_yi-2024.3.4.0.dist-info/RECORD
